giraffe_encryption/__init__.py
giraffe_encryption/ascii.py
giraffe_encryption/decrypt.py
giraffe_encryption/encrypt.py
giraffe_encryption/utils.py
giraffe_encryption/decryption/__init__.py
giraffe_encryption/decryption/decrypt.py
giraffe_encryption/encryption/__init__.py
giraffe_encryption/encryption/encrypt.py
giraffe_encryption/keys/__init__.py
giraffe_encryption/keys/keygen.py
giraffe_encryption/keys/read_key.py
giraffe_encryption_temp/__init__.py
giraffe_encryption_temp/ascii.py
giraffe_encryption_temp/decrypt.py
giraffe_encryption_temp/encrypt.py
giraffe_encryption_temp/utils.py
giraffe_encryption-0.1.3.dist-info/METADATA
giraffe_encryption-0.1.3.dist-info/WHEEL
giraffe_encryption-0.1.3.dist-info/entry_points.txt
giraffe_encryption-0.1.3.dist-info/top_level.txt
giraffe_encryption-0.1.3.dist-info/RECORD
