Metadata-Version: 2.1
Name: giraffe-encryption
Version: 0.1.3
Summary: UNKNOWN
Home-page: UNKNOWN
License: UNKNOWN
Platform: UNKNOWN
Requires-Dist: rsa>=4.9
